xknx/__init__.py
xknx/__version__.py
xknx/py.typed
xknx/xknx.py
xknx/cemi/__init__.py
xknx/cemi/cemi_frame.py
xknx/cemi/cemi_handler.py
xknx/cemi/const.py
xknx/core/__init__.py
xknx/core/connection_manager.py
xknx/core/connection_state.py
xknx/core/group_address_dpt.py
xknx/core/state_updater.py
xknx/core/task_registry.py
xknx/core/telegram_queue.py
xknx/core/value_reader.py
xknx/devices/__init__.py
xknx/devices/binary_sensor.py
xknx/devices/climate.py
xknx/devices/climate_mode.py
xknx/devices/cover.py
xknx/devices/datetime.py
xknx/devices/device.py
xknx/devices/devices.py
xknx/devices/expose_sensor.py
xknx/devices/fan.py
xknx/devices/light.py
xknx/devices/notification.py
xknx/devices/numeric_value.py
xknx/devices/raw_value.py
xknx/devices/scene.py
xknx/devices/sensor.py
xknx/devices/switch.py
xknx/devices/travelcalculator.py
xknx/devices/weather.py
xknx/dpt/__init__.py
xknx/dpt/dpt.py
xknx/dpt/dpt_1.py
xknx/dpt/dpt_10.py
xknx/dpt/dpt_11.py
xknx/dpt/dpt_12.py
xknx/dpt/dpt_13.py
xknx/dpt/dpt_14.py
xknx/dpt/dpt_16.py
xknx/dpt/dpt_17.py
xknx/dpt/dpt_18.py
xknx/dpt/dpt_19.py
xknx/dpt/dpt_20.py
xknx/dpt/dpt_232.py
xknx/dpt/dpt_235.py
xknx/dpt/dpt_242.py
xknx/dpt/dpt_251.py
xknx/dpt/dpt_29.py
xknx/dpt/dpt_3.py
xknx/dpt/dpt_5.py
xknx/dpt/dpt_6.py
xknx/dpt/dpt_7.py
xknx/dpt/dpt_8.py
xknx/dpt/dpt_9.py
xknx/dpt/payload.py
xknx/exceptions/__init__.py
xknx/exceptions/exception.py
xknx/io/__init__.py
xknx/io/connection.py
xknx/io/const.py
xknx/io/gateway_scanner.py
xknx/io/interface.py
xknx/io/ip_secure.py
xknx/io/knxip_interface.py
xknx/io/routing.py
xknx/io/self_description.py
xknx/io/tunnel.py
xknx/io/util.py
xknx/io/request_response/__init__.py
xknx/io/request_response/authenticate.py
xknx/io/request_response/connect.py
xknx/io/request_response/connectionstate.py
xknx/io/request_response/device_configuration.py
xknx/io/request_response/disconnect.py
xknx/io/request_response/request_response.py
xknx/io/request_response/session.py
xknx/io/request_response/tunnelling.py
xknx-3.13.0.dist-info/licenses/LICENSE
xknx-3.13.0.dist-info/METADATA
xknx-3.13.0.dist-info/WHEEL
xknx-3.13.0.dist-info/top_level.txt
xknx-3.13.0.dist-info/RECORD
