Metadata-Version: 2.4
Name: xknx
Version: 3.13.0
Summary: An Asynchronous Library for the KNX protocol. Documentation: https://xknx.io/
Author-email: Julius Mittenzwei <julius@mittenzwei.com>, Matthias Alphart <farmio@alphart.net>, Marvin Wichmann <me@marvin-wichmann.de>
License: MIT
Project-URL: homepage, https://xknx.io/
Project-URL: repository, https://github.com/XKNX/xknx.git
Keywords: KNX,EIB,Home Assistant,home automation
Classifier: Development Status :: 5 - Production/Stable
Classifier: Intended Audience :: Developers
Classifier: License :: OSI Approved :: MIT License
Classifier: Programming Language :: Python :: 3.10
Classifier: Programming Language :: Python :: 3.11
Classifier: Programming Language :: Python :: 3.12
Classifier: Programming Language :: Python :: 3.13
Classifier: Programming Language :: Python :: 3.14
Classifier: Topic :: System :: Hardware :: Hardware Drivers
Requires-Python: >=3.10.0
License-File: LICENSE
Requires-Dist: async_timeout>=4.0.0; python_version < "3.11"
Requires-Dist: typing_extensions; python_version < "3.11"
Requires-Dist: cryptography>=35.0.0
Requires-Dist: ifaddr>=0.1.7
Dynamic: license-file
